buffy/__init__.py
buffy_server-0.1.0.dist-info/WHEEL
buffy_server-0.1.0.dist-info/METADATA
buffy_server-0.1.0.dist-info/RECORD
