Metadata-Version: 2.1
Name: buffy-server
Version: 0.1.0
Summary: Shared framebuffer chat server
Author: Ossi Rajuvaara
Author-email: ossi@robocorp.com
Requires-Python: >=3.9,<4.0
Classifier: Programming Language :: Python :: 3
Classifier: Programming Language :: Python :: 3.10
Classifier: Programming Language :: Python :: 3.9
Requires-Dist: fastapi (>=0.70.0,<0.71.0)
